dual_finder/__init__.py
dual_finder/cnn/__init__.py
dual_finder/cnn/create_cnn.py
dual_finder/cnn/extract_feature_maps.py
dual_finder/cnn/load_model.py
dual_finder/cnn/train_cnn.py
dual_finder/optimize/__init__.py
dual_finder/optimize/optimize_hyperparameters.py
dual_finder/preprocess_data/__init__.py
dual_finder/preprocess_data/fits_utils.py
dual_finder/preprocess_data/process_data.py
dual_finder/visualize/__init__.py
dual_finder/visualize/visualize_performance.py
DualFinder-1.1.0.dist-info/METADATA
DualFinder-1.1.0.dist-info/WHEEL
DualFinder-1.1.0.dist-info/top_level.txt
DualFinder-1.1.0.dist-info/RECORD
